nonebot_plugin_addons_manager/__init__.py
nonebot_plugin_addons_manager/config.py
nonebot_plugin_addons_manager-0.1.3.dist-info/LICENSE
nonebot_plugin_addons_manager-0.1.3.dist-info/METADATA
nonebot_plugin_addons_manager-0.1.3.dist-info/WHEEL
nonebot_plugin_addons_manager-0.1.3.dist-info/RECORD
