Metadata-Version: 2.1
Name: nonebot-plugin-addons-manager
Version: 0.1.3
Summary: nonebot plugin that can help manage addons folder in valve's game
License: GPL-3.0-only
Author: ScorMax
Author-email: 1335900872@qq.com
Requires-Python: >=3.9,<4.0
Classifier: License :: OSI Approved :: GNU General Public License v3 (GPLv3)
Classifier: Programming Language :: Python :: 3
Classifier: Programming Language :: Python :: 3.9
Classifier: Programming Language :: Python :: 3.10
Classifier: Programming Language :: Python :: 3.11
Classifier: Programming Language :: Python :: 3.12
Classifier: Programming Language :: Python :: 3.13
Requires-Dist: aiohttp (>=3.11.10,<4.0.0)
Requires-Dist: nonebot-adapter-onebot (>=2.4.6,<3.0.0)
Requires-Dist: nonebot2 (>=2.4.0,<3.0.0)
